videolytics/__init__.py
videolytics/feature_extractor.py
videolytics/video_preprocessing.py
Videolytics-0.2.dist-info/LICENSE
Videolytics-0.2.dist-info/METADATA
Videolytics-0.2.dist-info/WHEEL
Videolytics-0.2.dist-info/top_level.txt
Videolytics-0.2.dist-info/RECORD
