Metadata-Version: 2.1
Name: Videolytics
Version: 0.2
Summary: Efficiently process videos
Home-page: https://github.com/Samran-Elahi/Videolytics
Author: Samran Elahi
Author-email: m.samranelahi@gmail.com
License: UNKNOWN
Project-URL: Bug Tracker, https://github.com/Samran-Elahi/Videolytics/issues
Platform: UNKNOWN
Classifier: Programming Language :: Python :: 3
Classifier: License :: OSI Approved :: MIT License
Classifier: Operating System :: OS Independent
Requires-Python: >=3.6
License-File: LICENSE
